nami_soccer_mcp_server/__init__.py
nami_soccer_mcp_server/soccer_server.py
nami_soccer_mcp_server-0.1.6.dist-info/METADATA
nami_soccer_mcp_server-0.1.6.dist-info/WHEEL
nami_soccer_mcp_server-0.1.6.dist-info/entry_points.txt
nami_soccer_mcp_server-0.1.6.dist-info/top_level.txt
nami_soccer_mcp_server-0.1.6.dist-info/RECORD
