Metadata-Version: 2.4
Name: nami-soccer-mcp-server
Version: 0.1.6
Summary: soccer-mcp-server fork
Requires-Python: >=3.11
Requires-Dist: fastmcp>=2.11.0
Requires-Dist: mcp>=1.9.0
